hippolyzer/__init__.py
hippolyzer/apps/__init__.py
hippolyzer/apps/addon_dialog.ui
hippolyzer/apps/filter_dialog.ui
hippolyzer/apps/message_builder.ui
hippolyzer/apps/model.py
hippolyzer/apps/proxy.py
hippolyzer/apps/proxy_gui.py
hippolyzer/apps/proxy_mainwindow.ui
hippolyzer/lib/__init__.py
hippolyzer/lib/base/__init__.py
hippolyzer/lib/base/anim_utils.py
hippolyzer/lib/base/colladatools.py
hippolyzer/lib/base/datatypes.py
hippolyzer/lib/base/events.py
hippolyzer/lib/base/exc.py
hippolyzer/lib/base/gltftools.py
hippolyzer/lib/base/helpers.py
hippolyzer/lib/base/inventory.py
hippolyzer/lib/base/jp2_utils.py
hippolyzer/lib/base/legacy_schema.py
hippolyzer/lib/base/llanim.py
hippolyzer/lib/base/llsd.py
hippolyzer/lib/base/mesh.py
hippolyzer/lib/base/mesh_skeleton.py
hippolyzer/lib/base/multidict.py
hippolyzer/lib/base/multiprocessing_utils.py
hippolyzer/lib/base/namevalue.py
hippolyzer/lib/base/objects.py
hippolyzer/lib/base/serialization.py
hippolyzer/lib/base/settings.py
hippolyzer/lib/base/templates.py
hippolyzer/lib/base/test_utils.py
hippolyzer/lib/base/transfer_manager.py
hippolyzer/lib/base/ui_helpers.py
hippolyzer/lib/base/vfs.py
hippolyzer/lib/base/wearables.py
hippolyzer/lib/base/xfer_manager.py
hippolyzer/lib/base/data/LICENSE-artwork.txt
hippolyzer/lib/base/data/avatar_lad.xml
hippolyzer/lib/base/data/avatar_skeleton.xml
hippolyzer/lib/base/data/male_collada_joints.xml
hippolyzer/lib/base/data/static_data.db2
hippolyzer/lib/base/data/static_index.db2
hippolyzer/lib/base/message/__init__.py
hippolyzer/lib/base/message/circuit.py
hippolyzer/lib/base/message/data_packer.py
hippolyzer/lib/base/message/llsd_msg_serializer.py
hippolyzer/lib/base/message/message.py
hippolyzer/lib/base/message/message_dot_xml.py
hippolyzer/lib/base/message/message_formatting.py
hippolyzer/lib/base/message/message_handler.py
hippolyzer/lib/base/message/msgtypes.py
hippolyzer/lib/base/message/template.py
hippolyzer/lib/base/message/template_dict.py
hippolyzer-0.17.1.dist-info/licenses/LICENSE.txt
hippolyzer-0.17.1.dist-info/licenses/NOTICE.md
hippolyzer-0.17.1.dist-info/METADATA
hippolyzer-0.17.1.dist-info/WHEEL
hippolyzer-0.17.1.dist-info/entry_points.txt
hippolyzer-0.17.1.dist-info/top_level.txt
hippolyzer-0.17.1.dist-info/RECORD
