Metadata-Version: 2.4
Name: hippolyzer
Version: 0.17.1
Summary: Analysis tools for SL-compatible virtual worlds
Author-email: Salad Dais <83434023+SaladDais@users.noreply.github.com>
License-Expression: LGPL-3.0-only
Project-URL: Homepage, https://github.com/SaladDais/Hippolyzer/
Classifier: Operating System :: MacOS
Classifier: Operating System :: Microsoft :: Windows
Classifier: Operating System :: POSIX
Classifier: Programming Language :: Python :: 3 :: Only
Classifier: Programming Language :: Python :: Implementation :: CPython
Classifier: Programming Language :: Python :: 3.12
Classifier: Programming Language :: Python :: 3.13
Classifier: Topic :: Software Development :: Libraries :: Python Modules
Classifier: Topic :: Software Development :: Testing
Classifier: Topic :: System :: Networking :: Monitoring
Requires-Python: >=3.12
License-File: LICENSE.txt
License-File: NOTICE.md
Requires-Dist: aiohttp<4.0.0
Requires-Dist: defusedxml
Requires-Dist: gltflib
Requires-Dist: Glymur<0.9.7
Requires-Dist: idna<3,>=2.5
Requires-Dist: lazy-object-proxy
Requires-Dist: llsd<1.1.0
Requires-Dist: numpy<2.0
Requires-Dist: pycollada
Requires-Dist: recordclass<0.24,>=0.23.1
Requires-Dist: transformations
Provides-Extra: proxy
Requires-Dist: arpeggio; extra == "proxy"
Requires-Dist: mitmproxy<12,>=11.0.0; extra == "proxy"
Requires-Dist: outleap<1.0; extra == "proxy"
Requires-Dist: ptpython<4.0; extra == "proxy"
Requires-Dist: Werkzeug<4.0; extra == "proxy"
Provides-Extra: gui
Requires-Dist: hippolyzer[proxy]; extra == "gui"
Requires-Dist: pyside6-essentials; extra == "gui"
Requires-Dist: qasync; extra == "gui"
Dynamic: license-file
